alfinx/__init__.py
alfinx/main.py
alfinx_utils-0.3.9.dist-info/licenses/LICENSE
alfinx_utils-0.3.9.dist-info/METADATA
alfinx_utils-0.3.9.dist-info/WHEEL
alfinx_utils-0.3.9.dist-info/top_level.txt
alfinx_utils-0.3.9.dist-info/RECORD
