Metadata-Version: 2.4
Name: alfinx_utils
Version: 0.3.9
Summary: HTTP headers auto detection tool.
Author: Maharram
Author-email: maharram@alfinx.com
Requires-Python: >=3.8
License-File: LICENSE
Requires-Dist: fastapi
Requires-Dist: httpx
Dynamic: author
Dynamic: author-email
Dynamic: description
Dynamic: description-content-type
Dynamic: license-file
Dynamic: requires-dist
Dynamic: requires-python
Dynamic: summary
